lukedrew_uvw_demo/__init__.py
lukedrew_uvw_demo/__main__.py
lukedrew_uvw_demo/example.py
lukedrew_uvw_demo/fail.py
lukedrew_uvw_demo/py.typed
lukedrew_uvw_demo_2/__init__.py
lukedrew_uvw_demo_2/py.typed
lukedrew_uvw_demo-0.1.0.dist-info/licenses/LICENSE
lukedrew_uvw_demo-0.1.0.dist-info/WHEEL
lukedrew_uvw_demo-0.1.0.dist-info/entry_points.txt
lukedrew_uvw_demo-0.1.0.dist-info/METADATA
lukedrew_uvw_demo-0.1.0.dist-info/RECORD
