Metadata-Version: 2.4
Name: lukedrew-uvw-demo
Version: 0.1.0
Summary: 
Keywords: 
Author: Lukasz A. Kadlubowski
Author-email: Lukasz A. Kadlubowski <lk@gmail.com>
License-Expression: MIT
License-File: LICENSE
Requires-Dist: lukedrew-bird-feeder
Requires-Dist: lukedrew-mahjong
Requires-Dist: lukedrew-seeds
Maintainer: Lukasz A. Kadlubowski
Maintainer-email: Lukasz A. Kadlubowski <lk@gmail.com>
Requires-Python: >=3.6
